{
  "date": "2026-01-07",
  "scrape_time": "2026-01-07T08:19:01.904004",
  "source": "igold.bg",
  "product_type": "silver",
  "products": [
    {
      "product_name": "250 гр. Сребърно Кюлче Argor-Heraeus Швейцария",
      "url": "https://igold.bg/srebarno-kyulche-250-g-argor-heraeus",
      "product_type": "bar",
      "total_weight_g": 250.0,
      "purity_per_mille": 999.5,
      "fine_silver_g": 250.0,
      "price_bgn": 1170.0,
      "price_eur": 598.21,
      "price_per_g_fine_bgn": 4.68,
      "price_per_g_fine_eur": 2.39,
      "buy_price_bgn": 1170.0,
      "sell_price_bgn": 0.0,
      "spread_percentage": ""
    },
    {
      "product_name": "500 гр. Сребърно Кюлче Valcambi Швейцария",
      "url": "https://igold.bg/500-g-srebarno-kyulche-valcambi",
      "product_type": "bar",
      "total_weight_g": 500.0,
      "purity_per_mille": 999.5,
      "fine_silver_g": 500.0,
      "price_bgn": 2448.0,
      "price_eur": 1251.64,
      "price_per_g_fine_bgn": 4.9,
      "price_per_g_fine_eur": 2.5,
      "buy_price_bgn": 2448.0,
      "sell_price_bgn": 0.0,
      "spread_percentage": ""
    },
    {
      "product_name": "31.1 гр. (1 toz.) Сребърно Кюлче Тор Royal Mint",
      "url": "https://igold.bg/srebarno-kyulche-1-oz-tor-royal-mint",
      "product_type": "bar",
      "total_weight_g": 31.1,
      "purity_per_mille": 999.9,
      "fine_silver_g": 31.1,
      "price_bgn": 154.0,
      "price_eur": 78.74,
      "price_per_g_fine_bgn": 4.95,
      "price_per_g_fine_eur": 2.53,
      "buy_price_bgn": 154.0,
      "sell_price_bgn": 0.0,
      "spread_percentage": ""
    },
    {
      "product_name": "100 гр. Сребърно Кюлче Argor-Heraeus Швейцария",
      "url": "https://igold.bg/srebarno-kyulche-100-g-argor-heraeus",
      "product_type": "bar",
      "total_weight_g": 100.0,
      "purity_per_mille": 999.5,
      "fine_silver_g": 100.0,
      "price_bgn": 507.0,
      "price_eur": 259.22,
      "price_per_g_fine_bgn": 5.07,
      "price_per_g_fine_eur": 2.59,
      "buy_price_bgn": 507.0,
      "sell_price_bgn": 0.0,
      "spread_percentage": ""
    },
    {
      "product_name": "31.1 гр. (1 toz.) Сребърна Монета Кругерранд",
      "url": "https://igold.bg/srebarna-moneta-1-oz-krugerrand",
      "product_type": "coin",
      "total_weight_g": 31.1,
      "purity_per_mille": 999.0,
      "fine_silver_g": 31.1,
      "price_bgn": 168.27,
      "price_eur": 86.04,
      "price_per_g_fine_bgn": 5.41,
      "price_per_g_fine_eur": 2.77,
      "buy_price_bgn": 168.27,
      "sell_price_bgn": 0.0,
      "spread_percentage": ""
    },
    {
      "product_name": "31.1 гр. ( 1 toz. ) Сребърна Монета Кленов Лист",
      "url": "https://igold.bg/srebarna-moneta-1-oz-klenov-list",
      "product_type": "coin",
      "total_weight_g": 31.1,
      "purity_per_mille": 999.0,
      "fine_silver_g": 31.1,
      "price_bgn": 168.94,
      "price_eur": 86.38,
      "price_per_g_fine_bgn": 5.43,
      "price_per_g_fine_eur": 2.78,
      "buy_price_bgn": 168.94,
      "sell_price_bgn": 0.0,
      "spread_percentage": ""
    },
    {
      "product_name": "31.1 гр. (1 toz.) Сребърна Монета Китайска Панда",
      "url": "https://igold.bg/srebarna-moneta-1-oz-panda",
      "product_type": "coin",
      "total_weight_g": 31.1,
      "purity_per_mille": 999.0,
      "fine_silver_g": 31.1,
      "price_bgn": 171.0,
      "price_eur": 87.43,
      "price_per_g_fine_bgn": 5.5,
      "price_per_g_fine_eur": 2.81,
      "buy_price_bgn": 171.0,
      "sell_price_bgn": 0.0,
      "spread_percentage": ""
    },
    {
      "product_name": "31.1 гр. (1 toz.) Сребърна Монета Мексикански Либертад",
      "url": "https://igold.bg/srebarna-moneta-1-oz-meksikanski-libertad",
      "product_type": "coin",
      "total_weight_g": 31.1,
      "purity_per_mille": 999.0,
      "fine_silver_g": 31.1,
      "price_bgn": 172.0,
      "price_eur": 87.94,
      "price_per_g_fine_bgn": 5.53,
      "price_per_g_fine_eur": 2.83,
      "buy_price_bgn": 172.0,
      "sell_price_bgn": 0.0,
      "spread_percentage": ""
    },
    {
      "product_name": "31.1 гр. (1 toz.) Сребърна Монета Австралийска Коала",
      "url": "https://igold.bg/srebarna-moneta-1-oz-koala-2020",
      "product_type": "coin",
      "total_weight_g": 31.1,
      "purity_per_mille": 999.0,
      "fine_silver_g": 31.1,
      "price_bgn": 174.0,
      "price_eur": 88.96,
      "price_per_g_fine_bgn": 5.59,
      "price_per_g_fine_eur": 2.86,
      "buy_price_bgn": 174.0,
      "sell_price_bgn": 0.0,
      "spread_percentage": ""
    },
    {
      "product_name": "30 гр. Сребърна Монета Китайска Панда",
      "url": "https://igold.bg/srebarna-moneta-30-g-panda",
      "product_type": "coin",
      "total_weight_g": 30.0,
      "purity_per_mille": 999.0,
      "fine_silver_g": 30.0,
      "price_bgn": 170.0,
      "price_eur": 86.92,
      "price_per_g_fine_bgn": 5.67,
      "price_per_g_fine_eur": 2.9,
      "buy_price_bgn": 170.0,
      "sell_price_bgn": 0.0,
      "spread_percentage": ""
    },
    {
      "product_name": "31.1 гр. ( 1 toz. ) Сребърна Монета Филхармония",
      "url": "https://igold.bg/srebarna-moneta-1-oz-filharmoniya",
      "product_type": "coin",
      "total_weight_g": 31.1,
      "purity_per_mille": 999.0,
      "fine_silver_g": 31.1,
      "price_bgn": 183.24,
      "price_eur": 93.69,
      "price_per_g_fine_bgn": 5.89,
      "price_per_g_fine_eur": 3.01,
      "buy_price_bgn": 167.87,
      "sell_price_bgn": 183.24,
      "spread_percentage": 8.39
    },
    {
      "product_name": "31.1 гр. (1 toz.) Сребърна Монета Британия",
      "url": "https://igold.bg/1-oz-srebarna-moneta-britania",
      "product_type": "coin",
      "total_weight_g": 31.1,
      "purity_per_mille": 999.0,
      "fine_silver_g": 31.1,
      "price_bgn": 183.91,
      "price_eur": 94.03,
      "price_per_g_fine_bgn": 5.91,
      "price_per_g_fine_eur": 3.02,
      "buy_price_bgn": 168.27,
      "sell_price_bgn": 183.91,
      "spread_percentage": 8.5
    },
    {
      "product_name": "31.1 гр. ( 1 toz. ) Сребърна Монета Кенгуру",
      "url": "https://igold.bg/srebarna-moneta-1-oz-kenguru",
      "product_type": "coin",
      "total_weight_g": 31.1,
      "purity_per_mille": 999.0,
      "fine_silver_g": 31.1,
      "price_bgn": 183.91,
      "price_eur": 94.03,
      "price_per_g_fine_bgn": 5.91,
      "price_per_g_fine_eur": 3.02,
      "buy_price_bgn": 168.27,
      "sell_price_bgn": 183.91,
      "spread_percentage": 8.5
    },
    {
      "product_name": "31.1 гр. ( 1 toz. ) Сребърна Монета Американски Орел",
      "url": "https://igold.bg/srebarna-moneta-1-oz-amerikanski-orel",
      "product_type": "coin",
      "total_weight_g": 31.1,
      "purity_per_mille": 999.0,
      "fine_silver_g": 31.1,
      "price_bgn": 195.95,
      "price_eur": 100.19,
      "price_per_g_fine_bgn": 6.3,
      "price_per_g_fine_eur": 3.22,
      "buy_price_bgn": 169.61,
      "sell_price_bgn": 195.95,
      "spread_percentage": 13.44
    },
    {
      "product_name": "311 гр. (10 toz.) Сребърно Кюлче Локи Royal Mint",
      "url": "https://igold.bg/srebarno-kyulche-10-oz-loki-royal-mint",
      "product_type": "bar",
      "total_weight_g": 311.0,
      "purity_per_mille": 999.9,
      "fine_silver_g": 311.0,
      "price_bgn": 1958.0,
      "price_eur": 1001.11,
      "price_per_g_fine_bgn": 6.3,
      "price_per_g_fine_eur": 3.22,
      "buy_price_bgn": 1429.0,
      "sell_price_bgn": 1958.0,
      "spread_percentage": 27.02
    },
    {
      "product_name": "30 гр. Сребърна Монета Китайска Панда 2026",
      "url": "https://igold.bg/srebarna-moneta-30-g-panda-2026",
      "product_type": "coin",
      "total_weight_g": 30.0,
      "purity_per_mille": 999.0,
      "fine_silver_g": 30.0,
      "price_bgn": 209.0,
      "price_eur": 106.86,
      "price_per_g_fine_bgn": 6.97,
      "price_per_g_fine_eur": 3.56,
      "buy_price_bgn": 148.0,
      "sell_price_bgn": 209.0,
      "spread_percentage": 29.19
    },
    {
      "product_name": "31.1 гр. (1 toz.) Сребърно Кюлче Локи Royal Mint",
      "url": "https://igold.bg/srebarno-kyulche-1-oz-royal-mint-loki",
      "product_type": "bar",
      "total_weight_g": 31.1,
      "purity_per_mille": 999.9,
      "fine_silver_g": 31.1,
      "price_bgn": 225.0,
      "price_eur": 115.04,
      "price_per_g_fine_bgn": 7.23,
      "price_per_g_fine_eur": 3.7,
      "buy_price_bgn": 154.0,
      "sell_price_bgn": 225.0,
      "spread_percentage": 31.56
    },
    {
      "product_name": "62.2 гр. (2 toz.) Сребърна Монета Австралийски Лунар Кон 2026",
      "url": "https://igold.bg/srebarna-moneta-2-oz-lunar-kon-2026",
      "product_type": "coin",
      "total_weight_g": 62.2,
      "purity_per_mille": 999.0,
      "fine_silver_g": 62.2,
      "price_bgn": 465.0,
      "price_eur": 237.75,
      "price_per_g_fine_bgn": 7.48,
      "price_per_g_fine_eur": 3.82,
      "buy_price_bgn": 321.0,
      "sell_price_bgn": 465.0,
      "spread_percentage": 30.97
    },
    {
      "product_name": "31.1 гр. ( 1 toz. ) Сребърна Монета Австралийска Коала 2025 RAM",
      "url": "https://igold.bg/srebarna-moneta-1-oz-koala-2025",
      "product_type": "coin",
      "total_weight_g": 31.1,
      "purity_per_mille": 999.9,
      "fine_silver_g": 31.1,
      "price_bgn": 238.0,
      "price_eur": 121.69,
      "price_per_g_fine_bgn": 7.65,
      "price_per_g_fine_eur": 3.91,
      "buy_price_bgn": 150.0,
      "sell_price_bgn": 238.0,
      "spread_percentage": 36.97
    },
    {
      "product_name": "31.1 гр. ( 1 toz. ) Сребърна Монета Австралийски Лунар Кон 2026",
      "url": "https://igold.bg/srebarna-moneta-1-oz-lunar-kon-2026",
      "product_type": "coin",
      "total_weight_g": 31.1,
      "purity_per_mille": 999.0,
      "fine_silver_g": 31.1,
      "price_bgn": 238.0,
      "price_eur": 121.69,
      "price_per_g_fine_bgn": 7.65,
      "price_per_g_fine_eur": 3.91,
      "buy_price_bgn": 160.0,
      "sell_price_bgn": 238.0,
      "spread_percentage": 32.77
    },
    {
      "product_name": "31.1 гр. ( 1 toz. ) Сребърна Монета Австралийски Лунар Змия 2025",
      "url": "https://igold.bg/srebarna-moneta-1-oz-lunar-zmiya-2025",
      "product_type": "coin",
      "total_weight_g": 31.1,
      "purity_per_mille": 999.0,
      "fine_silver_g": 31.1,
      "price_bgn": 241.0,
      "price_eur": 123.22,
      "price_per_g_fine_bgn": 7.75,
      "price_per_g_fine_eur": 3.96,
      "buy_price_bgn": 174.0,
      "sell_price_bgn": 241.0,
      "spread_percentage": 27.8
    },
    {
      "product_name": "62.2 гр. ( 2 toz. ) Сребърна Монета Канадска Гъска 2025",
      "url": "https://igold.bg/srebarna-moneta-2-oz-kanadska-gaska-2025",
      "product_type": "coin",
      "total_weight_g": 62.2,
      "purity_per_mille": 999.0,
      "fine_silver_g": 62.2,
      "price_bgn": 514.0,
      "price_eur": 262.8,
      "price_per_g_fine_bgn": 8.26,
      "price_per_g_fine_eur": 4.23,
      "buy_price_bgn": 294.0,
      "sell_price_bgn": 514.0,
      "spread_percentage": 42.8
    },
    {
      "product_name": "31.1 гр. (1 toz.) Сребърна Монета Сомалийски Леопард 2023",
      "url": "https://igold.bg/srebarna-moneta-1-oz-somaliyski-leopard-2023",
      "product_type": "coin",
      "total_weight_g": 31.1,
      "purity_per_mille": 999.0,
      "fine_silver_g": 31.1,
      "price_bgn": 273.0,
      "price_eur": 139.58,
      "price_per_g_fine_bgn": 8.78,
      "price_per_g_fine_eur": 4.49,
      "buy_price_bgn": 160.0,
      "sell_price_bgn": 273.0,
      "spread_percentage": 41.39
    },
    {
      "product_name": "31.1 гр. (1 toz.) Сребърна Монета Сомалийски Слон 2026",
      "url": "https://igold.bg/srebarna-moneta-1-oz-somaliyski-slon-2026",
      "product_type": "coin",
      "total_weight_g": 31.1,
      "purity_per_mille": 999.0,
      "fine_silver_g": 31.1,
      "price_bgn": 273.0,
      "price_eur": 139.58,
      "price_per_g_fine_bgn": 8.78,
      "price_per_g_fine_eur": 4.49,
      "buy_price_bgn": 160.0,
      "sell_price_bgn": 273.0,
      "spread_percentage": 41.39
    },
    {
      "product_name": "62.2 гр. ( 2 toz. ) Сребърна Монета Бик и Мечка Канада 2025",
      "url": "https://igold.bg/srebarna-moneta-2-oz-bik-i-mechka-2025",
      "product_type": "coin",
      "total_weight_g": 62.2,
      "purity_per_mille": 999.0,
      "fine_silver_g": 62.2,
      "price_bgn": 546.0,
      "price_eur": 279.17,
      "price_per_g_fine_bgn": 8.78,
      "price_per_g_fine_eur": 4.49,
      "buy_price_bgn": 294.0,
      "sell_price_bgn": 546.0,
      "spread_percentage": 46.15
    },
    {
      "product_name": "31.1 гр. ( 1 toz. ) Правоъгълна Сребърна Монета Дракон Австралия 2025",
      "url": "https://igold.bg/1-oz-pravoagalna-srebarna-moneta-drakon-2025",
      "product_type": "coin",
      "total_weight_g": 31.1,
      "purity_per_mille": 999.9,
      "fine_silver_g": 31.1,
      "price_bgn": 284.0,
      "price_eur": 145.21,
      "price_per_g_fine_bgn": 9.13,
      "price_per_g_fine_eur": 4.67,
      "buy_price_bgn": 150.0,
      "sell_price_bgn": 284.0,
      "spread_percentage": 47.18
    },
    {
      "product_name": "31.1 гр. (1 toz.) Сребърен Токен Pacman 45 Годишнина Pamp Швейцария",
      "url": "https://igold.bg/srebaren-token-1-oz-pacman-45-godishnina-pamp",
      "product_type": "bar",
      "total_weight_g": 31.1,
      "purity_per_mille": 999.9,
      "fine_silver_g": 31.1,
      "price_bgn": 321.0,
      "price_eur": 164.12,
      "price_per_g_fine_bgn": 10.32,
      "price_per_g_fine_eur": 5.28,
      "buy_price_bgn": 214.0,
      "sell_price_bgn": 321.0,
      "spread_percentage": 33.33
    },
    {
      "product_name": "31.1 гр. (1 toz.) Сребърна Монета Австралийскo Бръмби 2025",
      "url": "https://igold.bg/srebarna-moneta-1-oz-avstraliysko-brumby-2025",
      "product_type": "coin",
      "total_weight_g": 31.1,
      "purity_per_mille": 999.0,
      "fine_silver_g": 31.1,
      "price_bgn": 321.0,
      "price_eur": 164.12,
      "price_per_g_fine_bgn": 10.32,
      "price_per_g_fine_eur": 5.28,
      "buy_price_bgn": 174.0,
      "sell_price_bgn": 321.0,
      "spread_percentage": 45.79
    },
    {
      "product_name": "15.55 гр. ( 1/2 toz. )Сребърна Монета Австралийски Лунар Кон 2026",
      "url": "https://igold.bg/srebarna-moneta-1-2-oz-lunar-kon-2026",
      "product_type": "coin",
      "total_weight_g": 15.55,
      "purity_per_mille": 999.0,
      "fine_silver_g": 15.55,
      "price_bgn": 161.0,
      "price_eur": 82.32,
      "price_per_g_fine_bgn": 10.35,
      "price_per_g_fine_eur": 5.29,
      "buy_price_bgn": 93.0,
      "sell_price_bgn": 161.0,
      "spread_percentage": 42.24
    },
    {
      "product_name": "31.1 гр. ( 1 toz. )Сребърна Монета Iron Мan vs. Ultron Marvel & Pamp Швейцария 2025",
      "url": "https://igold.bg/srebarna-moneta-1-oz-iron-man-vs-ultron-marvel",
      "product_type": "coin",
      "total_weight_g": 31.1,
      "purity_per_mille": 999.9,
      "fine_silver_g": 31.1,
      "price_bgn": 334.0,
      "price_eur": 170.77,
      "price_per_g_fine_bgn": 10.74,
      "price_per_g_fine_eur": 5.49,
      "buy_price_bgn": 214.0,
      "sell_price_bgn": 334.0,
      "spread_percentage": 35.93
    },
    {
      "product_name": "31.1 гр. (1 toz.) Сребърна Монета Кругерранд 50 Годишнина PROOF 2017",
      "url": "https://igold.bg/srebarna-moneta-1-oz-krugerrand-proof-2017",
      "product_type": "coin",
      "total_weight_g": 31.1,
      "purity_per_mille": 999.0,
      "fine_silver_g": 31.1,
      "price_bgn": 334.0,
      "price_eur": 170.77,
      "price_per_g_fine_bgn": 10.74,
      "price_per_g_fine_eur": 5.49,
      "buy_price_bgn": 187.0,
      "sell_price_bgn": 334.0,
      "spread_percentage": 44.01
    },
    {
      "product_name": "62.2 гр. (2 toz.) Сребърна Монета Австралийски Лунар Вол 2021",
      "url": "https://igold.bg/srebarna-moneta-2-oz-lunar-vol-2021",
      "product_type": "coin",
      "total_weight_g": 62.2,
      "purity_per_mille": 999.0,
      "fine_silver_g": 62.2,
      "price_bgn": 669.0,
      "price_eur": 342.05,
      "price_per_g_fine_bgn": 10.76,
      "price_per_g_fine_eur": 5.5,
      "buy_price_bgn": 374.0,
      "sell_price_bgn": 669.0,
      "spread_percentage": 44.1
    },
    {
      "product_name": "62.2 гр. ( 2 toz. ) Сребърна 3D Монета Thor Kra Koom Marvel 2025",
      "url": "https://igold.bg/3d-srebarna-moneta-2-oz-thor-kra-koom-2025",
      "product_type": "coin",
      "total_weight_g": 62.2,
      "purity_per_mille": 999.0,
      "fine_silver_g": 62.2,
      "price_bgn": 706.0,
      "price_eur": 360.97,
      "price_per_g_fine_bgn": 11.35,
      "price_per_g_fine_eur": 5.8,
      "buy_price_bgn": 534.0,
      "sell_price_bgn": 706.0,
      "spread_percentage": 24.36
    },
    {
      "product_name": "31.1 гр. ( 1 toz. ) Сребърно Кюлче Междузвездни Войни Тъмната Страна Royal Mint",
      "url": "https://igold.bg/srebarno-kyulche-1-oz-star-wars-tamnata-strana",
      "product_type": "bar",
      "total_weight_g": 31.1,
      "purity_per_mille": 999.9,
      "fine_silver_g": 31.1,
      "price_bgn": 369.0,
      "price_eur": 188.67,
      "price_per_g_fine_bgn": 11.86,
      "price_per_g_fine_eur": 6.07,
      "buy_price_bgn": 155.0,
      "sell_price_bgn": 369.0,
      "spread_percentage": 57.99
    },
    {
      "product_name": "15.55 гр. (1/2 toz.) Сребърна Монета Австралийски Лунар Змия 2025",
      "url": "https://igold.bg/srebarna-moneta-1-2-oz-lunar-zmiya-2025",
      "product_type": "coin",
      "total_weight_g": 15.55,
      "purity_per_mille": 999.0,
      "fine_silver_g": 15.55,
      "price_bgn": 193.0,
      "price_eur": 98.68,
      "price_per_g_fine_bgn": 12.41,
      "price_per_g_fine_eur": 6.35,
      "buy_price_bgn": 93.0,
      "sell_price_bgn": 193.0,
      "spread_percentage": 51.81
    },
    {
      "product_name": "31.1 гр. ( 1 toz. )Сребърно Кюлче Pamp Швейцария Лунар Бяла Змия 2025",
      "url": "https://igold.bg/srebarno-kyulche-1-oz-pamp-byala-zmiya-2025",
      "product_type": "bar",
      "total_weight_g": 31.1,
      "purity_per_mille": 999.0,
      "fine_silver_g": 31.1,
      "price_bgn": 398.0,
      "price_eur": 203.49,
      "price_per_g_fine_bgn": 12.8,
      "price_per_g_fine_eur": 6.54,
      "buy_price_bgn": 171.0,
      "sell_price_bgn": 398.0,
      "spread_percentage": 57.04
    },
    {
      "product_name": "31.1 гр. (1 toz.) Сребърна Монета Star Trek USS Enterprise User Manual 2025",
      "url": "https://igold.bg/srebarna-moneta-1-oz-star-trek-uss-2025",
      "product_type": "coin",
      "total_weight_g": 31.1,
      "purity_per_mille": 999.0,
      "fine_silver_g": 31.1,
      "price_bgn": 401.0,
      "price_eur": 205.03,
      "price_per_g_fine_bgn": 12.89,
      "price_per_g_fine_eur": 6.59,
      "buy_price_bgn": 267.0,
      "sell_price_bgn": 401.0,
      "spread_percentage": 33.42
    },
    {
      "product_name": "31.1 гр. (1 toz.) Сребърна Монета Stranger Things Netflix Сезон 1 2026",
      "url": "https://igold.bg/srebarna-moneta-1-oz-stranger-things-sez-1-2026",
      "product_type": "coin",
      "total_weight_g": 31.1,
      "purity_per_mille": 999.0,
      "fine_silver_g": 31.1,
      "price_bgn": 401.0,
      "price_eur": 205.03,
      "price_per_g_fine_bgn": 12.89,
      "price_per_g_fine_eur": 6.59,
      "buy_price_bgn": 267.0,
      "sell_price_bgn": 401.0,
      "spread_percentage": 33.42
    },
    {
      "product_name": "31.1 гр. (1 toz.) Сребърна Монета Stranger Things Netflix Сезон 2 2026",
      "url": "https://igold.bg/srebarna-moneta-1-oz-stranger-things-sez-2-2026",
      "product_type": "coin",
      "total_weight_g": 31.1,
      "purity_per_mille": 999.0,
      "fine_silver_g": 31.1,
      "price_bgn": 401.0,
      "price_eur": 205.03,
      "price_per_g_fine_bgn": 12.89,
      "price_per_g_fine_eur": 6.59,
      "buy_price_bgn": 267.0,
      "sell_price_bgn": 401.0,
      "spread_percentage": 33.42
    },
    {
      "product_name": "31.1 гр. (1 toz.) Сребърна Монета Star Trek The Vulcan Salute 2025",
      "url": "https://igold.bg/srebarna-moneta-1-oz-vulcan-salute-2025",
      "product_type": "coin",
      "total_weight_g": 31.1,
      "purity_per_mille": 999.0,
      "fine_silver_g": 31.1,
      "price_bgn": 401.0,
      "price_eur": 205.03,
      "price_per_g_fine_bgn": 12.89,
      "price_per_g_fine_eur": 6.59,
      "buy_price_bgn": 267.0,
      "sell_price_bgn": 401.0,
      "spread_percentage": 33.42
    },
    {
      "product_name": "15.55 гр. (1/2 toz.) Сребърна Монета Австралийски Лунар Кон за Новородено 2026",
      "url": "https://igold.bg/1-2-oz-srebaren-lunar-kon-2026-za-novorodeno",
      "product_type": "coin",
      "total_weight_g": 15.55,
      "purity_per_mille": 999.0,
      "fine_silver_g": 15.55,
      "price_bgn": 217.0,
      "price_eur": 110.95,
      "price_per_g_fine_bgn": 13.95,
      "price_per_g_fine_eur": 7.14,
      "buy_price_bgn": 100.0,
      "sell_price_bgn": 217.0,
      "spread_percentage": 53.92
    },
    {
      "product_name": "46.65гр. (1.5 toz.) Сребърна Монета Картина Marvel Black Panther 2025",
      "url": "https://igold.bg/srebarna-moneta-1-5-oz-marvel-black-panther-2025",
      "product_type": "coin",
      "total_weight_g": 46.65,
      "purity_per_mille": 999.0,
      "fine_silver_g": 46.65,
      "price_bgn": 674.0,
      "price_eur": 344.61,
      "price_per_g_fine_bgn": 14.45,
      "price_per_g_fine_eur": 7.39,
      "buy_price_bgn": 501.0,
      "sell_price_bgn": 674.0,
      "spread_percentage": 25.67
    },
    {
      "product_name": "46.65гр. ( 1.5 toz. ) Сребърна Монета Картина Marvel Thor Ragnarok 2025",
      "url": "https://igold.bg/srebarna-moneta-46-65-g-thor-ragnarok-2025",
      "product_type": "coin",
      "total_weight_g": 46.65,
      "purity_per_mille": 999.0,
      "fine_silver_g": 46.65,
      "price_bgn": 674.0,
      "price_eur": 344.61,
      "price_per_g_fine_bgn": 14.45,
      "price_per_g_fine_eur": 7.39,
      "buy_price_bgn": 501.0,
      "sell_price_bgn": 674.0,
      "spread_percentage": 25.67
    },
    {
      "product_name": "31.1 гр. (1 toz.) Сребърна Монета Гарфилд Първо Издание 2025",
      "url": "https://igold.bg/srebarna-moneta-1-oz-garfield-2025",
      "product_type": "coin",
      "total_weight_g": 31.1,
      "purity_per_mille": 999.0,
      "fine_silver_g": 31.1,
      "price_bgn": 465.0,
      "price_eur": 237.75,
      "price_per_g_fine_bgn": 14.95,
      "price_per_g_fine_eur": 7.64,
      "buy_price_bgn": 267.0,
      "sell_price_bgn": 465.0,
      "spread_percentage": 42.58
    },
    {
      "product_name": "31.1 гр. (1 toz.) Сребърно Кюлче Pamp Швейцария Лакшми 2025",
      "url": "https://igold.bg/srebarno-kyulche-1-oz-lakshmi-pamp-2025",
      "product_type": "bar",
      "total_weight_g": 31.1,
      "purity_per_mille": 999.0,
      "fine_silver_g": 31.1,
      "price_bgn": 465.0,
      "price_eur": 237.75,
      "price_per_g_fine_bgn": 14.95,
      "price_per_g_fine_eur": 7.64,
      "buy_price_bgn": 361.0,
      "sell_price_bgn": 465.0,
      "spread_percentage": 22.37
    },
    {
      "product_name": "31.1 гр. (1 toz.) Сребърна Монета Мечо Пух Любовта към Меда 2025",
      "url": "https://igold.bg/srebarna-moneta-1-oz-mecho-puh-2025",
      "product_type": "coin",
      "total_weight_g": 31.1,
      "purity_per_mille": 999.0,
      "fine_silver_g": 31.1,
      "price_bgn": 482.0,
      "price_eur": 246.44,
      "price_per_g_fine_bgn": 15.5,
      "price_per_g_fine_eur": 7.92,
      "buy_price_bgn": 267.0,
      "sell_price_bgn": 482.0,
      "spread_percentage": 44.61
    },
    {
      "product_name": "31.1 гр. ( 1 toz. ) Сребърна Монета Цветен Австралийски Лунар Кон 2026",
      "url": "https://igold.bg/srebarna-moneta-1-oz-tzveten-lunar-kon-2026",
      "product_type": "coin",
      "total_weight_g": 31.1,
      "purity_per_mille": 999.0,
      "fine_silver_g": 31.1,
      "price_bgn": 498.0,
      "price_eur": 254.62,
      "price_per_g_fine_bgn": 16.01,
      "price_per_g_fine_eur": 8.19,
      "buy_price_bgn": 334.0,
      "sell_price_bgn": 498.0,
      "spread_percentage": 32.93
    },
    {
      "product_name": "31.1 гр. (1 toz.) Сребърна Монета Картина Dungeon's & Dragons Player's Handbook 2025",
      "url": "https://igold.bg/srebarna-moneta-1-oz-dungeons-and-dragons-2025",
      "product_type": "coin",
      "total_weight_g": 31.1,
      "purity_per_mille": 999.0,
      "fine_silver_g": 31.1,
      "price_bgn": 514.0,
      "price_eur": 262.8,
      "price_per_g_fine_bgn": 16.53,
      "price_per_g_fine_eur": 8.45,
      "buy_price_bgn": 267.0,
      "sell_price_bgn": 514.0,
      "spread_percentage": 48.05
    },
    {
      "product_name": "31.1 гр. (1 toz.) Сребърна Монета Картина Star Wars The Death Star 2025",
      "url": "https://igold.bg/srebarna-moneta-1-oz-star-wars-death-star-2025",
      "product_type": "coin",
      "total_weight_g": 31.1,
      "purity_per_mille": 999.0,
      "fine_silver_g": 31.1,
      "price_bgn": 530.0,
      "price_eur": 270.98,
      "price_per_g_fine_bgn": 17.04,
      "price_per_g_fine_eur": 8.71,
      "buy_price_bgn": 401.0,
      "sell_price_bgn": 530.0,
      "spread_percentage": 24.34
    },
    {
      "product_name": "31.1 гр. (1 toz.) Сребърна Монета Картина Star Wars The Fighter 2025",
      "url": "https://igold.bg/srebarna-moneta-1-oz-star-wars-the-fighter",
      "product_type": "coin",
      "total_weight_g": 31.1,
      "purity_per_mille": 999.0,
      "fine_silver_g": 31.1,
      "price_bgn": 530.0,
      "price_eur": 270.98,
      "price_per_g_fine_bgn": 17.04,
      "price_per_g_fine_eur": 8.71,
      "buy_price_bgn": 401.0,
      "sell_price_bgn": 530.0,
      "spread_percentage": 24.34
    },
    {
      "product_name": "31.1 гр. (1 toz.) Сребърна Монета Картина Фантастичната Четворка Doctor Doom Marvel 2025",
      "url": "https://igold.bg/srebarna-1-oz-fantastichnata-chetvorka-2025",
      "product_type": "coin",
      "total_weight_g": 31.1,
      "purity_per_mille": 999.0,
      "fine_silver_g": 31.1,
      "price_bgn": 562.0,
      "price_eur": 287.35,
      "price_per_g_fine_bgn": 18.07,
      "price_per_g_fine_eur": 9.24,
      "buy_price_bgn": 267.0,
      "sell_price_bgn": 562.0,
      "spread_percentage": 52.49
    },
    {
      "product_name": "31.1 гр. (1 toz.) Сребърна Монета Позлатен Австралийски Лунар Кон 2026",
      "url": "https://igold.bg/srebarna-moneta-1-oz-lunar-kon-2026-pozlaten",
      "product_type": "coin",
      "total_weight_g": 31.1,
      "purity_per_mille": 999.0,
      "fine_silver_g": 31.1,
      "price_bgn": 562.0,
      "price_eur": 287.35,
      "price_per_g_fine_bgn": 18.07,
      "price_per_g_fine_eur": 9.24,
      "buy_price_bgn": 267.0,
      "sell_price_bgn": 562.0,
      "spread_percentage": 52.49
    },
    {
      "product_name": "10 гр. Сребърно Кюлче Pamp Швейцария Лунар Бяла Змия 2025",
      "url": "https://igold.bg/srebarno-kyulche-10-g-pamp-byala-zmiya-2025",
      "product_type": "bar",
      "total_weight_g": 10.0,
      "purity_per_mille": 999.0,
      "fine_silver_g": 10.0,
      "price_bgn": 191.0,
      "price_eur": 97.66,
      "price_per_g_fine_bgn": 19.1,
      "price_per_g_fine_eur": 9.77,
      "buy_price_bgn": 120.0,
      "sell_price_bgn": 191.0,
      "spread_percentage": 37.17
    },
    {
      "product_name": "93.3 гр. (3x1 toz.) Трио Комплект Сребърни Монети Австралийски Лунар Кон 2026",
      "url": "https://igold.bg/trio-srebarni-moneti-3-x-1-oz-lunar-2026-kon",
      "product_type": "bar",
      "total_weight_g": 3.0,
      "purity_per_mille": 999.0,
      "fine_silver_g": 2.997,
      "price_bgn": 1348.0,
      "price_eur": 689.22,
      "price_per_g_fine_bgn": 449.78,
      "price_per_g_fine_eur": 229.97,
      "buy_price_bgn": 962.0,
      "sell_price_bgn": 1348.0,
      "spread_percentage": 28.64
    },
    {
      "product_name": "1 кг Сребърно Кюлче Argor- Heraeus Швейцария",
      "url": "https://igold.bg/srebarno-kyulche-1-kg-argor-heraeus",
      "product_type": "bar",
      "total_weight_g": 1.0,
      "purity_per_mille": 999.5,
      "fine_silver_g": 0.9995,
      "price_bgn": 4638.0,
      "price_eur": 2371.37,
      "price_per_g_fine_bgn": 4640.32,
      "price_per_g_fine_eur": 2372.56,
      "buy_price_bgn": 4638.0,
      "sell_price_bgn": 0.0,
      "spread_percentage": ""
    },
    {
      "product_name": "1 кг Сребърна Монета Австралийска Коала",
      "url": "https://igold.bg/srebarna-moneta-1-kg-koala",
      "product_type": "coin",
      "total_weight_g": 1.0,
      "purity_per_mille": 999.0,
      "fine_silver_g": 0.999,
      "price_bgn": 5282.0,
      "price_eur": 2700.64,
      "price_per_g_fine_bgn": 5287.29,
      "price_per_g_fine_eur": 2703.34,
      "buy_price_bgn": 5282.0,
      "sell_price_bgn": 0.0,
      "spread_percentage": ""
    },
    {
      "product_name": "1 кг Сребърна Монета Австралийска Кукабура",
      "url": "https://igold.bg/srebarna-moneta-1-kg-kukabura",
      "product_type": "coin",
      "total_weight_g": 1.0,
      "purity_per_mille": 999.0,
      "fine_silver_g": 0.999,
      "price_bgn": 5282.0,
      "price_eur": 2700.64,
      "price_per_g_fine_bgn": 5287.29,
      "price_per_g_fine_eur": 2703.34,
      "buy_price_bgn": 5282.0,
      "sell_price_bgn": 0.0,
      "spread_percentage": ""
    },
    {
      "product_name": "1 кг Сребърно Кюлче Valcambi Швейцария",
      "url": "https://igold.bg/srebarno-kyulche-1-kg-valcambi",
      "product_type": "bar",
      "total_weight_g": 1.0,
      "purity_per_mille": 999.5,
      "fine_silver_g": 0.9995,
      "price_bgn": 5858.0,
      "price_eur": 2995.15,
      "price_per_g_fine_bgn": 5860.93,
      "price_per_g_fine_eur": 2996.65,
      "buy_price_bgn": 4638.0,
      "sell_price_bgn": 5858.0,
      "spread_percentage": 20.83
    },
    {
      "product_name": "1 кг Сребърна Монета Цветен Австралийски Лунар Змия 2025",
      "url": "https://igold.bg/srebarna-moneta-1-kg-tzveten-lunar-zmiya-2025",
      "product_type": "coin",
      "total_weight_g": 1.0,
      "purity_per_mille": 999.0,
      "fine_silver_g": 0.999,
      "price_bgn": 6451.0,
      "price_eur": 3298.34,
      "price_per_g_fine_bgn": 6457.46,
      "price_per_g_fine_eur": 3301.64,
      "buy_price_bgn": 4938.0,
      "sell_price_bgn": 6451.0,
      "spread_percentage": 23.45
    },
    {
      "product_name": "Кюлчета с Нумизматичен Потенциал",
      "url": "https://igold.bg/kyulcheta-s-numizmatichen-potenitzial",
      "product_type": "bar",
      "total_weight_g": "",
      "purity_per_mille": 999.9,
      "fine_silver_g": "",
      "price_bgn": 7792.0,
      "price_eur": "",
      "price_per_g_fine_bgn": "",
      "price_per_g_fine_eur": "",
      "buy_price_bgn": "",
      "sell_price_bgn": "",
      "spread_percentage": ""
    },
    {
      "product_name": "2 x ??.? гр. (? toz.) Сребърни или Златни Монети Тайнствена Кутия Marvel The Infinity Saga",
      "url": "https://igold.bg/srebarni-i-zlatni-moneti-marvel-taynstvena-kutiya",
      "product_type": "bar",
      "total_weight_g": "",
      "purity_per_mille": 999.0,
      "fine_silver_g": "",
      "price_bgn": 1412.0,
      "price_eur": 721.94,
      "price_per_g_fine_bgn": "",
      "price_per_g_fine_eur": "",
      "buy_price_bgn": 1202.0,
      "sell_price_bgn": 1412.0,
      "spread_percentage": 14.87
    },
    {
      "product_name": "Инвестиционни Златни Кюлчета",
      "url": "https://igold.bg/zlatni-kyulcheta-investitsionni",
      "product_type": "bar",
      "total_weight_g": "",
      "purity_per_mille": 999.9,
      "fine_silver_g": "",
      "price_bgn": 260.0,
      "price_eur": "",
      "price_per_g_fine_bgn": "",
      "price_per_g_fine_eur": "",
      "buy_price_bgn": "",
      "sell_price_bgn": "",
      "spread_percentage": ""
    },
    {
      "product_name": "Подаръчни Златни Кюлчета",
      "url": "https://igold.bg/zlatni-kyulcheta-za-podarak",
      "product_type": "bar",
      "total_weight_g": "",
      "purity_per_mille": 999.9,
      "fine_silver_g": "",
      "price_bgn": 7792.0,
      "price_eur": "",
      "price_per_g_fine_bgn": "",
      "price_per_g_fine_eur": "",
      "buy_price_bgn": "",
      "sell_price_bgn": "",
      "spread_percentage": ""
    },
    {
      "product_name": "Нумизматични Кюлчета",
      "url": "https://igold.bg/zlatni-numizmatichni-kyulcheta",
      "product_type": "bar",
      "total_weight_g": "",
      "purity_per_mille": 999.9,
      "fine_silver_g": "",
      "price_bgn": 2020.0,
      "price_eur": "",
      "price_per_g_fine_bgn": "",
      "price_per_g_fine_eur": "",
      "buy_price_bgn": "",
      "sell_price_bgn": "",
      "spread_percentage": ""
    }
  ]
}