{
  "report_type": "daily",
  "metal_type": "gold",
  "report_date": "2025-12-31",
  "statistics": {
    "today_date": "2025-12-31",
    "yesterday_date": "2025-12-30",
    "top_5_count": 5,
    "average_price_per_gram": 238.75,
    "yesterday_average": 240.12,
    "price_change_pct": -0.57,
    "trend": "stable",
    "product_types": {
      "bars": 5,
      "coins": 0
    },
    "new_products_count": 0,
    "total_products_today": 238,
    "best_deals": [
      {
        "product_name": "250 гр. Златно Кюлче Valcambi Швейцария",
        "url": "https://igold.bg/zlatno-kyulche-250-g-valcambi",
        "product_type": "bar",
        "total_weight_g": 250.0,
        "purity_per_mille": "999.9/1000",
        "fine_gold_g": 250.0,
        "sell_price_bgn": 59348.0,
        "buy_price_bgn": 58277.0,
        "sell_price_eur": 30344.15,
        "buy_price_eur": 29796.56,
        "price_per_g_fine_bgn": 237.39,
        "price_per_g_fine_eur": 121.38,
        "spread_percentage": 1.8
      },
      {
        "product_name": "100 гр. Златно Кюлче Valcambi Швейцария",
        "url": "https://igold.bg/zlatno-kyulche-valcambi-100-g",
        "product_type": "bar",
        "total_weight_g": 100.0,
        "purity_per_mille": "999.9/1000",
        "fine_gold_g": 100.0,
        "sell_price_bgn": 23781.0,
        "buy_price_bgn": 23438.0,
        "sell_price_eur": 12159.03,
        "buy_price_eur": 11983.66,
        "price_per_g_fine_bgn": 237.81,
        "price_per_g_fine_eur": 121.59,
        "spread_percentage": 1.44
      },
      {
        "product_name": "100 гр. Златно Кюлче Argor-Heraeus Швейцария Холограмна Защита",
        "url": "https://igold.bg/zlatno-kyulche-100-g-argor-heraeus-kinebar",
        "product_type": "bar",
        "total_weight_g": 100.0,
        "purity_per_mille": "999.9/1000",
        "fine_gold_g": 100.0,
        "sell_price_bgn": 23796.0,
        "buy_price_bgn": 23453.0,
        "sell_price_eur": 12166.7,
        "buy_price_eur": 11991.33,
        "price_per_g_fine_bgn": 237.96,
        "price_per_g_fine_eur": 121.67,
        "spread_percentage": 1.44
      },
      {
        "product_name": "50 гр. Златно Кюлче Valcambi Швейцария",
        "url": "https://igold.bg/zlatno-kyulche-valcambi-50-g",
        "product_type": "bar",
        "total_weight_g": 50.0,
        "purity_per_mille": "999.9/1000",
        "fine_gold_g": 50.0,
        "sell_price_bgn": 12009.0,
        "buy_price_bgn": 11934.0,
        "sell_price_eur": 6140.1,
        "buy_price_eur": 6101.76,
        "price_per_g_fine_bgn": 240.18,
        "price_per_g_fine_eur": 122.8,
        "spread_percentage": 0.62
      },
      {
        "product_name": "50 гр. Златно Кюлче Argor- Heraeus Швейцария Холограмна Защита",
        "url": "https://igold.bg/zlatno-kyulche-50-g-argor-heraeus-kinebar",
        "product_type": "bar",
        "total_weight_g": 50.0,
        "purity_per_mille": "999.9/1000",
        "fine_gold_g": 50.0,
        "sell_price_bgn": 12021.0,
        "buy_price_bgn": 11945.0,
        "sell_price_eur": 6146.24,
        "buy_price_eur": 6107.38,
        "price_per_g_fine_bgn": 240.42,
        "price_per_g_fine_eur": 122.92,
        "spread_percentage": 0.63
      }
    ],
    "affordable_deals": [
      {
        "product_name": "20 гр. Златно Кюлче Argor-Heraeus Швейцария Холограмна Защита",
        "url": "https://igold.bg/zlatno-kyulche-20-g-argor-heraeus-kinebar",
        "product_type": "bar",
        "total_weight_g": 20.0,
        "purity_per_mille": "999.9/1000",
        "fine_gold_g": 20.0,
        "sell_price_bgn": 4889.0,
        "buy_price_bgn": 4862.0,
        "sell_price_eur": 2499.71,
        "buy_price_eur": 2485.9,
        "price_per_g_fine_bgn": 244.45,
        "price_per_g_fine_eur": 124.99,
        "spread_percentage": 0.55
      },
      {
        "product_name": "20 гр. Златно Кюлче Valcambi Швейцария",
        "url": "https://igold.bg/zlatno-kyulche-valcambi-20-g",
        "product_type": "bar",
        "total_weight_g": 20.0,
        "purity_per_mille": "999.9/1000",
        "fine_gold_g": 20.0,
        "sell_price_bgn": 4889.0,
        "buy_price_bgn": 4862.0,
        "sell_price_eur": 2499.71,
        "buy_price_eur": 2485.9,
        "price_per_g_fine_bgn": 244.45,
        "price_per_g_fine_eur": 124.99,
        "spread_percentage": 0.55
      },
      {
        "product_name": "20 гр. Златно Кюлче Valcambi Швейцария",
        "url": "https://igold.bg/zlatno-kyulche-valcambi-20-g",
        "product_type": "bar",
        "total_weight_g": 20.0,
        "purity_per_mille": "999.9/1000",
        "fine_gold_g": 20.0,
        "sell_price_bgn": 4889.0,
        "buy_price_bgn": 4862.0,
        "sell_price_eur": 2499.71,
        "buy_price_eur": 2485.9,
        "price_per_g_fine_bgn": 244.45,
        "price_per_g_fine_eur": 124.99,
        "spread_percentage": 0.55
      },
      {
        "product_name": "7.99 гр. Златна Монета Британски Суверен Джордж V 1911-1932",
        "url": "https://igold.bg/zlaten-britanski-suveren-george-1911-1932",
        "product_type": "coin",
        "total_weight_g": 7.99,
        "purity_per_mille": "916.7/1000",
        "fine_gold_g": 7.32,
        "sell_price_bgn": 1799.0,
        "buy_price_bgn": 1757.0,
        "sell_price_eur": 919.81,
        "buy_price_eur": 898.34,
        "price_per_g_fine_bgn": 245.77,
        "price_per_g_fine_eur": 125.66,
        "spread_percentage": 2.33
      },
      {
        "product_name": "7.99 гр. Златна Монета Британски Суверен Едуард VII 1902-1910",
        "url": "https://igold.bg/zlaten-souvereign-eduard-1902-1910",
        "product_type": "coin",
        "total_weight_g": 7.99,
        "purity_per_mille": "916.7/1000",
        "fine_gold_g": 7.32,
        "sell_price_bgn": 1799.0,
        "buy_price_bgn": 1757.0,
        "sell_price_eur": 919.81,
        "buy_price_eur": 898.34,
        "price_per_g_fine_bgn": 245.77,
        "price_per_g_fine_eur": 125.66,
        "spread_percentage": 2.33
      },
      {
        "product_name": "6.45 гр. Златна Монета 20 Френски Франка Наполеон III 1853- 1860",
        "url": "https://igold.bg/20-zlatni-franka-napoleon",
        "product_type": "coin",
        "total_weight_g": 6.45,
        "purity_per_mille": "900/1000",
        "fine_gold_g": 5.81,
        "sell_price_bgn": 1428.0,
        "buy_price_bgn": 1411.0,
        "sell_price_eur": 730.12,
        "buy_price_eur": 721.43,
        "price_per_g_fine_bgn": 245.78,
        "price_per_g_fine_eur": 125.67,
        "spread_percentage": 1.19
      },
      {
        "product_name": "6.45 гр. Златна Монета 20 Френски Франка Наполеон III с Венец 1861- 1870",
        "url": "https://igold.bg/zlaten-napoleon-s-venetz-6-45-g",
        "product_type": "coin",
        "total_weight_g": 6.45,
        "purity_per_mille": "900/1000",
        "fine_gold_g": 5.81,
        "sell_price_bgn": 1428.0,
        "buy_price_bgn": 1411.0,
        "sell_price_eur": 730.12,
        "buy_price_eur": 721.43,
        "price_per_g_fine_bgn": 245.78,
        "price_per_g_fine_eur": 125.67,
        "spread_percentage": 1.19
      },
      {
        "product_name": "6.45 гр. Златна Монета 20 Швейцарски Франка Вренели 1897-1949",
        "url": "https://igold.bg/20-zlatni-franka-vreneli",
        "product_type": "coin",
        "total_weight_g": 6.45,
        "purity_per_mille": "900/1000",
        "fine_gold_g": 5.81,
        "sell_price_bgn": 1429.0,
        "buy_price_bgn": 1402.0,
        "sell_price_eur": 730.64,
        "buy_price_eur": 716.83,
        "price_per_g_fine_bgn": 245.96,
        "price_per_g_fine_eur": 125.76,
        "spread_percentage": 1.89
      },
      {
        "product_name": "6.45 гр. Златна Монета 20 Френски Франка Гениус 1871- 1898",
        "url": "https://igold.bg/20-franka-zlaten-genius",
        "product_type": "coin",
        "total_weight_g": 6.45,
        "purity_per_mille": "900/1000",
        "fine_gold_g": 5.81,
        "sell_price_bgn": 1430.0,
        "buy_price_bgn": 1397.0,
        "sell_price_eur": 731.15,
        "buy_price_eur": 714.27,
        "price_per_g_fine_bgn": 246.13,
        "price_per_g_fine_eur": 125.84,
        "spread_percentage": 2.31
      },
      {
        "product_name": "6.45 гр. Златна Монета 20 Френски Франка Мариана 1898- 1914",
        "url": "https://igold.bg/20-zlatni-franka-mariana",
        "product_type": "coin",
        "total_weight_g": 6.45,
        "purity_per_mille": "900/1000",
        "fine_gold_g": 5.81,
        "sell_price_bgn": 1430.0,
        "buy_price_bgn": 1399.0,
        "sell_price_eur": 731.15,
        "buy_price_eur": 715.3,
        "price_per_g_fine_bgn": 246.13,
        "price_per_g_fine_eur": 125.84,
        "spread_percentage": 2.17
      }
    ],
    "live_price_today": null,
    "live_price_yesterday": null,
    "live_price_change_pct": null
  }
}